jupyterlab_spellchecker/__init__.py
jupyterlab_spellchecker/_version.py
jupyterlab_spellchecker/dictionaries.py
jupyterlab_spellchecker/handlers.py
jupyterlab_spellchecker/tests/test_dictionaries.py
jupyterlab_spellchecker-0.8.3.data/data/etc/jupyter/jupyter_notebook_config.d/jupyterlab-spellchecker.json
jupyterlab_spellchecker-0.8.3.data/data/etc/jupyter/jupyter_server_config.d/jupyterlab-spellchecker.json
jupyterlab_spellchecker-0.8.3.data/data/share/jupyter/dictionaries/README.txt
jupyterlab_spellchecker-0.8.3.data/data/share/jupyter/dictionaries/README_de_ALL_frami.txt
jupyterlab_spellchecker-0.8.3.data/data/share/jupyter/dictionaries/README_en_AU.txt
jupyterlab_spellchecker-0.8.3.data/data/share/jupyter/dictionaries/README_en_CA.txt
jupyterlab_spellchecker-0.8.3.data/data/share/jupyter/dictionaries/README_en_GB-ise.txt
jupyterlab_spellchecker-0.8.3.data/data/share/jupyter/dictionaries/README_en_US.txt
jupyterlab_spellchecker-0.8.3.data/data/share/jupyter/dictionaries/README_es_ES.txt
jupyterlab_spellchecker-0.8.3.data/data/share/jupyter/dictionaries/README_fr.txt
jupyterlab_spellchecker-0.8.3.data/data/share/jupyter/dictionaries/README_pt_PT.txt
jupyterlab_spellchecker-0.8.3.data/data/share/jupyter/dictionaries/de_AT_frami.aff
jupyterlab_spellchecker-0.8.3.data/data/share/jupyter/dictionaries/de_AT_frami.dic
jupyterlab_spellchecker-0.8.3.data/data/share/jupyter/dictionaries/de_CH_frami.aff
jupyterlab_spellchecker-0.8.3.data/data/share/jupyter/dictionaries/de_CH_frami.dic
jupyterlab_spellchecker-0.8.3.data/data/share/jupyter/dictionaries/de_DE_frami.aff
jupyterlab_spellchecker-0.8.3.data/data/share/jupyter/dictionaries/de_DE_frami.dic
jupyterlab_spellchecker-0.8.3.data/data/share/jupyter/dictionaries/en_AU.aff
jupyterlab_spellchecker-0.8.3.data/data/share/jupyter/dictionaries/en_AU.dic
jupyterlab_spellchecker-0.8.3.data/data/share/jupyter/dictionaries/en_CA.aff
jupyterlab_spellchecker-0.8.3.data/data/share/jupyter/dictionaries/en_CA.dic
jupyterlab_spellchecker-0.8.3.dist-info/METADATA
jupyterlab_spellchecker-0.8.3.dist-info/WHEEL
jupyterlab_spellchecker-0.8.3.dist-info/licenses/LICENSE
jupyterlab_spellchecker-0.8.3.dist-info/RECORD
